gammarer/aws_frontend_web_app_deploy_stack/__init__.py
gammarer/aws_frontend_web_app_deploy_stack/py.typed
gammarer/aws_frontend_web_app_deploy_stack/_jsii/__init__.py
gammarer/aws_frontend_web_app_deploy_stack/_jsii/aws-frontend-web-app-deploy-stack@1.1.7.jsii.tgz
gammarer.aws_frontend_web_app_deploy_stack-1.1.7.dist-info/LICENSE
gammarer.aws_frontend_web_app_deploy_stack-1.1.7.dist-info/METADATA
gammarer.aws_frontend_web_app_deploy_stack-1.1.7.dist-info/WHEEL
gammarer.aws_frontend_web_app_deploy_stack-1.1.7.dist-info/top_level.txt
gammarer.aws_frontend_web_app_deploy_stack-1.1.7.dist-info/RECORD
